LICENSE.md
ebay_feedsdk/.gitignore
ebay_feedsdk/__init__.py
ebay_feedsdk/config/__init__.py
ebay_feedsdk/config/config_request.py
ebay_feedsdk/constants/__init__.py
ebay_feedsdk/constants/feed_constants.py
ebay_feedsdk/ebay_download_example.py
ebay_feedsdk/enums/__init__.py
ebay_feedsdk/enums/config_enums.py
ebay_feedsdk/enums/feed_enums.py
ebay_feedsdk/enums/file_enums.py
ebay_feedsdk/errors/__init__.py
ebay_feedsdk/errors/custom_exceptions.py
ebay_feedsdk/examples/__init__.py
ebay_feedsdk/examples/config_examples.py
ebay_feedsdk/feed.py
ebay_feedsdk/feed_cli.py
ebay_feedsdk/filter/__init__.py
ebay_feedsdk/filter/feed_filter.py
ebay_feedsdk/oauthclient/__init__.py
ebay_feedsdk/oauthclient/credentialutil.py
ebay_feedsdk/oauthclient/model/__init__.py
ebay_feedsdk/oauthclient/model/model.py
ebay_feedsdk/oauthclient/model/util.py
ebay_feedsdk/oauthclient/oauth2api.py
ebay_feedsdk/run_tests.py
ebay_feedsdk/sample-config/config-file-download
ebay_feedsdk/sample-config/config-file-download-filter
ebay_feedsdk/sample-config/config-file-filter
ebay_feedsdk/sample-config/config-file-query-only
ebay_feedsdk/tests/oauthclient/config/ebay-config-sample.json
ebay_feedsdk/tests/oauthclient/config/ebay-config-sample.yaml
ebay_feedsdk/tests/oauthclient/config/test-config-sample.json
ebay_feedsdk/tests/oauthclient/config/test-config-sample.yaml
ebay_feedsdk/tests/oauthclient/test_get_application_token.py
ebay_feedsdk/tests/oauthclient/test_get_user_access_token.py
ebay_feedsdk/tests/oauthclient/test_util.py
ebay_feedsdk/tests/sdk/__init__.py
ebay_feedsdk/tests/sdk/test-data/test_config
ebay_feedsdk/tests/sdk/test-data/test_json
ebay_feedsdk/tests/sdk/test_config_request.py
ebay_feedsdk/tests/sdk/test_date_utils.py
ebay_feedsdk/tests/sdk/test_feed_filter.py
ebay_feedsdk/tests/sdk/test_feed_request.py
ebay_feedsdk/tests/sdk/test_file_utils.py
ebay_feedsdk/tests/sdk/test_filter_utils.py
ebay_feedsdk/tests/sdk/test_logging_utils.py
ebay_feedsdk/utils/__init__.py
ebay_feedsdk-0.2.6.dist-info/LICENSE.md
ebay_feedsdk-0.2.6.dist-info/WHEEL
ebay_feedsdk-0.2.6.dist-info/METADATA
ebay_feedsdk-0.2.6.dist-info/RECORD
