Metadata-Version: 2.1
Name: ebay-feedsdk
Version: 0.2.6
Summary: Port of https://github.com/eBay/FeedSDK-Python and https://github.com/eBay/ebay-oauth-python-client to python3
Home-page: https://github.com/taxaos/FeedSDK-Python
License: Apache-2.0
Keywords: ebay,ebay-feedsdk
Author: Lars Erler
Author-email: lars@xaospage.de
Requires-Python: >=3.7.1,<4.0.0
Classifier: Environment :: Console
Classifier: License :: OSI Approved :: Apache Software License
Classifier: Programming Language :: Python :: 3
Classifier: Programming Language :: Python :: 3.8
Classifier: Programming Language :: Python :: 3.9
Classifier: Topic :: Software Development :: Libraries :: Python Modules
Requires-Dist: PyYAML (>=5.4.1,<6.0.0)
Requires-Dist: SQLAlchemy (>=1.3.8,<2.0.0)
Requires-Dist: aenum (>=3.00,<4.0)
Requires-Dist: certifi (>=2020.12.5,<2021.0.0)
Requires-Dist: pandas (>=1.1.1,<2.0.0)
Requires-Dist: requests (>=2.25.1,<3.0.0)
Requires-Dist: urllib3 (>=1.26.4,<2.0.0)
Project-URL: Repository, https://github.com/taxaos/FeedSDK-Python
